minitor/__init__.py
minitor/main.py
minitor-1.0.3.dist-info/LICENSE
minitor-1.0.3.dist-info/METADATA
minitor-1.0.3.dist-info/WHEEL
minitor-1.0.3.dist-info/entry_points.txt
minitor-1.0.3.dist-info/top_level.txt
minitor-1.0.3.dist-info/RECORD
