Metadata-Version: 2.1
Name: minitor
Version: 1.0.3
Summary: A minimal monitoring tool
Home-page: https://git.iamthefij.com/iamthefij/minitor
Author: Ian Fijolek
Author-email: ian@iamthefij.com
License: UNKNOWN
Download-URL: https://git.iamthefij.com/iamthefij/minitor/archive/master.tar.gz
Keywords: minitor monitoring alerting
Platform: UNKNOWN
Classifier: Development Status :: 5 - Production/Stable
Classifier: Intended Audience :: Developers
Classifier: Intended Audience :: System Administrators
Classifier: Topic :: System :: Monitoring
Classifier: License :: OSI Approved :: Apache Software License
Classifier: Programming Language :: Python :: 3
Classifier: Programming Language :: Python :: 3.4
Classifier: Programming Language :: Python :: 3.5
Classifier: Programming Language :: Python :: 3.6
Classifier: Programming Language :: Python :: 3.7
Requires-Dist: prometheus-client
Requires-Dist: yamlenv
